frizz/__init__.py
frizz/errors.py
frizz/_internal/__init__.py
frizz/_internal/agent.py
frizz/_internal/tools.py
frizz/_internal/types/__init__.py
frizz/_internal/types/response.py
frizz-0.2.0.dist-info/METADATA
frizz-0.2.0.dist-info/WHEEL
frizz-0.2.0.dist-info/RECORD
