Metadata-Version: 2.4
Name: frizz
Version: 0.2.0
Summary: A tool-assisted AI conversationalist.
Author-email: Nash Taylor <nash@chelle.ai>, Joshua Cook <joshua@chelle.ai>, Michael Sankur <michael@chelle.ai>
Requires-Python: >=3.12
Requires-Dist: aikernel==0.2.1
